ban_converter/__init__.py
ban_converter/bban_to_iban.py
ban_converter/iban_to_bban.py
ban_converter-0.0.2.dist-info/LICENSE
ban_converter-0.0.2.dist-info/METADATA
ban_converter-0.0.2.dist-info/WHEEL
ban_converter-0.0.2.dist-info/top_level.txt
ban_converter-0.0.2.dist-info/RECORD
